[{"confidence": "0.9243", "file_id": "89", "bbox": "45 86 409 541"}, {"confidence": "0.9159", "file_id": "29", "bbox": "74 12 580 385"}, {"confidence": "0.9129", "file_id": "71", "bbox": "97 30 326 343"}, {"confidence": "0.9096", "file_id": "3", "bbox": "1 33 520 403"}, {"confidence": "0.9043", "file_id": "148", "bbox": "59 6 486 401"}, {"confidence": "0.8984", "file_id": "131", "bbox": "85 0 385 327"}, {"confidence": "0.8893", "file_id": "85", "bbox": "137 147 573 459"}, {"confidence": "0.8860", "file_id": "81", "bbox": "172 3 540 424"}, {"confidence": "0.8799", "file_id": "72", "bbox": "137 64 522 468"}, {"confidence": "0.8795", "file_id": "35", "bbox": "267 78 639 477"}, {"confidence": "0.8774", "file_id": "114", "bbox": "325 26 592 409"}, {"confidence": "0.8739", "file_id": "143", "bbox": "0 2 466 477"}, {"confidence": "0.8732", "file_id": "10", "bbox": "0 0 444 414"}, {"confidence": "0.8703", "file_id": "34", "bbox": "64 12 505 422"}, {"confidence": "0.8672", "file_id": "154", "bbox": "200 76 618 337"}, {"confidence": "0.8668", "file_id": "100", "bbox": "130 88 620 532"}, {"confidence": "0.8654", "file_id": "123", "bbox": "110 79 352 419"}, {"confidence": "0.8629", "file_id": "37", "bbox": "29 58 493 391"}, {"confidence": "0.8619", "file_id": "174", "bbox": "190 117 363 330"}, {"confidence": "0.8601", "file_id": "59", "bbox": "97 55 472 571"}, {"confidence": "0.8583", "file_id": "74", "bbox": "184 112 417 442"}, {"confidence": "0.8575", "file_id": "106", "bbox": "20 190 430 623"}, {"confidence": "0.8563", "file_id": "90", "bbox": "156 33 455 612"}, {"confidence": "0.8502", "file_id": "12", "bbox": "5 5 367 482"}, {"confidence": "0.8496", "file_id": "53", "bbox": "20 153 337 491"}, {"confidence": "0.8461", "file_id": "127", "bbox": "121 6 374 639"}, {"confidence": "0.8460", "file_id": "134", "bbox": "2 22 499 293"}, {"confidence": "0.8445", "file_id": "75", "bbox": "362 281 461 367"}, {"confidence": "0.8381", "file_id": "94", "bbox": "8 0 622 396"}, {"confidence": "0.8355", "file_id": "7", "bbox": "126 230 489 548"}, {"confidence": "0.8319", "file_id": "128", "bbox": "4 102 514 605"}, {"confidence": "0.8310", "file_id": "147", "bbox": "203 347 461 614"}, {"confidence": "0.8289", "file_id": "159", "bbox": "226 141 486 313"}, {"confidence": "0.8271", "file_id": "82", "bbox": "0 82 428 450"}, {"confidence": "0.8249", "file_id": "157", "bbox": "149 215 470 553"}, {"confidence": "0.8232", "file_id": "11", "bbox": "18 86 608 479"}, {"confidence": "0.8230", "file_id": "65", "bbox": "34 12 321 627"}, {"confidence": "0.8204", "file_id": "111", "bbox": "9 104 221 393"}, {"confidence": "0.8181", "file_id": "6", "bbox": "220 110 388 412"}, {"confidence": "0.8181", "file_id": "23", "bbox": "6 0 562 639"}, {"confidence": "0.8179", "file_id": "49", "bbox": "168 333 346 507"}, {"confidence": "0.8118", "file_id": "44", "bbox": "154 108 393 533"}, {"confidence": "0.8097", "file_id": "162", "bbox": "0 422 130 610"}, {"confidence": "0.8093", "file_id": "141", "bbox": "138 37 297 265"}, {"confidence": "0.8083", "file_id": "133", "bbox": "280 135 424 306"}, {"confidence": "0.8059", "file_id": "76", "bbox": "188 48 622 330"}, {"confidence": "0.8055", "file_id": "149", "bbox": "61 80 592 308"}, {"confidence": "0.8024", "file_id": "171", "bbox": "256 139 405 221"}, {"confidence": "0.8011", "file_id": "19", "bbox": "63 36 498 456"}, {"confidence": "0.8006", "file_id": "55", "bbox": "246 131 355 223"}, {"confidence": "0.7992", "file_id": "16", "bbox": "267 102 479 390"}, {"confidence": "0.7981", "file_id": "105", "bbox": "85 183 257 419"}, {"confidence": "0.7966", "file_id": "30", "bbox": "281 154 489 494"}, {"confidence": "0.7956", "file_id": "126", "bbox": "166 197 496 363"}, {"confidence": "0.7935", "file_id": "47", "bbox": "271 200 425 473"}, {"confidence": "0.7933", "file_id": "99", "bbox": "148 19 483 326"}, {"confidence": "0.7927", "file_id": "21", "bbox": "3 109 319 522"}, {"confidence": "0.7894", "file_id": "116", "bbox": "434 74 618 360"}, {"confidence": "0.7856", "file_id": "31", "bbox": "245 169 348 377"}, {"confidence": "0.7844", "file_id": "96", "bbox": "508 211 585 349"}, {"confidence": "0.7793", "file_id": "124", "bbox": "50 388 191 516"}, {"confidence": "0.7782", "file_id": "107", "bbox": "3 0 527 639"}, {"confidence": "0.7778", "file_id": "129", "bbox": "256 155 595 354"}, {"confidence": "0.7766", "file_id": "115", "bbox": "150 225 258 324"}, {"confidence": "0.7759", "file_id": "46", "bbox": "111 0 464 639"}, {"confidence": "0.7756", "file_id": "0", "bbox": "234 352 332 412"}, {"confidence": "0.7742", "file_id": "67", "bbox": "298 255 358 360"}, {"confidence": "0.7693", "file_id": "104", "bbox": "260 90 600 421"}, {"confidence": "0.7674", "file_id": "141", "bbox": "335 198 580 422"}, {"confidence": "0.7660", "file_id": "164", "bbox": "48 496 131 577"}, {"confidence": "0.7648", "file_id": "86", "bbox": "227 298 292 336"}, {"confidence": "0.7645", "file_id": "136", "bbox": "218 199 451 301"}, {"confidence": "0.7639", "file_id": "165", "bbox": "99 23 283 224"}, {"confidence": "0.7636", "file_id": "151", "bbox": "112 26 209 127"}, {"confidence": "0.7633", "file_id": "95", "bbox": "27 81 175 226"}, {"confidence": "0.7630", "file_id": "18", "bbox": "16 316 279 592"}, {"confidence": "0.7624", "file_id": "170", "bbox": "394 68 606 280"}, {"confidence": "0.7623", "file_id": "33", "bbox": "201 58 356 281"}, {"confidence": "0.7616", "file_id": "20", "bbox": "63 198 289 608"}, {"confidence": "0.7594", "file_id": "60", "bbox": "207 148 291 294"}, {"confidence": "0.7567", "file_id": "63", "bbox": "28 74 302 265"}, {"confidence": "0.7522", "file_id": "32", "bbox": "8 68 321 186"}, {"confidence": "0.7455", "file_id": "156", "bbox": "161 386 278 576"}, {"confidence": "0.7449", "file_id": "117", "bbox": "318 221 402 275"}, {"confidence": "0.7440", "file_id": "140", "bbox": "83 91 172 162"}, {"confidence": "0.7435", "file_id": "45", "bbox": "26 35 210 144"}, {"confidence": "0.7431", "file_id": "97", "bbox": "83 287 231 484"}, {"confidence": "0.7426", "file_id": "146", "bbox": "62 119 255 366"}, {"confidence": "0.7423", "file_id": "62", "bbox": "133 186 272 275"}, {"confidence": "0.7418", "file_id": "132", "bbox": "221 110 390 280"}, {"confidence": "0.7368", "file_id": "50", "bbox": "128 126 520 414"}, {"confidence": "0.7357", "file_id": "64", "bbox": "162 146 205 227"}, {"confidence": "0.7348", "file_id": "54", "bbox": "55 234 313 517"}, {"confidence": "0.7338", "file_id": "24", "bbox": "134 41 357 277"}, {"confidence": "0.7331", "file_id": "80", "bbox": "508 168 567 239"}, {"confidence": "0.7312", "file_id": "87", "bbox": "0 25 635 417"}, {"confidence": "0.7310", "file_id": "28", "bbox": "4 112 537 345"}, {"confidence": "0.7306", "file_id": "68", "bbox": "103 103 459 467"}, {"confidence": "0.7302", "file_id": "130", "bbox": "349 143 430 310"}, {"confidence": "0.7267", "file_id": "167", "bbox": "337 237 456 353"}, {"confidence": "0.7265", "file_id": "41", "bbox": "157 51 494 404"}, {"confidence": "0.7224", "file_id": "102", "bbox": "172 156 355 327"}, {"confidence": "0.7204", "file_id": "95", "bbox": "325 225 466 366"}, {"confidence": "0.7178", "file_id": "145", "bbox": "69 216 262 328"}, {"confidence": "0.7173", "file_id": "168", "bbox": "0 175 253 473"}, {"confidence": "0.7104", "file_id": "110", "bbox": "271 22 549 385"}, {"confidence": "0.7080", "file_id": "93", "bbox": "201 352 290 554"}, {"confidence": "0.6990", "file_id": "98", "bbox": "232 149 471 457"}, {"confidence": "0.6982", "file_id": "56", "bbox": "118 177 473 639"}, {"confidence": "0.6966", "file_id": "160", "bbox": "434 153 606 365"}, {"confidence": "0.6958", "file_id": "79", "bbox": "111 289 198 344"}, {"confidence": "0.6954", "file_id": "6", "bbox": "444 0 570 161"}, {"confidence": "0.6953", "file_id": "69", "bbox": "294 406 403 478"}, {"confidence": "0.6934", "file_id": "169", "bbox": "6 241 333 607"}, {"confidence": "0.6930", "file_id": "25", "bbox": "239 263 381 345"}, {"confidence": "0.6927", "file_id": "150", "bbox": "130 174 233 318"}, {"confidence": "0.6908", "file_id": "109", "bbox": "28 488 99 625"}, {"confidence": "0.6907", "file_id": "142", "bbox": "8 195 217 469"}, {"confidence": "0.6901", "file_id": "118", "bbox": "432 262 478 319"}, {"confidence": "0.6821", "file_id": "176", "bbox": "0 40 425 413"}, {"confidence": "0.6769", "file_id": "98", "bbox": "36 123 143 254"}, {"confidence": "0.6674", "file_id": "9", "bbox": "204 22 622 348"}, {"confidence": "0.6660", "file_id": "118", "bbox": "46 117 327 307"}, {"confidence": "0.6576", "file_id": "135", "bbox": "0 274 458 570"}, {"confidence": "0.6436", "file_id": "137", "bbox": "168 100 441 350"}, {"confidence": "0.6420", "file_id": "8", "bbox": "152 287 250 482"}, {"confidence": "0.6342", "file_id": "88", "bbox": "104 53 162 176"}, {"confidence": "0.6219", "file_id": "42", "bbox": "61 69 292 231"}, {"confidence": "0.6203", "file_id": "175", "bbox": "271 182 638 364"}, {"confidence": "0.6170", "file_id": "39", "bbox": "2 14 430 348"}, {"confidence": "0.6143", "file_id": "22", "bbox": "175 281 219 324"}, {"confidence": "0.6134", "file_id": "125", "bbox": "214 58 506 398"}, {"confidence": "0.6102", "file_id": "122", "bbox": "16 72 218 351"}, {"confidence": "0.6063", "file_id": "144", "bbox": "261 41 412 187"}, {"confidence": "0.6035", "file_id": "42", "bbox": "38 55 469 250"}, {"confidence": "0.5952", "file_id": "138", "bbox": "36 321 207 499"}, {"confidence": "0.5923", "file_id": "58", "bbox": "190 231 284 443"}, {"confidence": "0.5908", "file_id": "17", "bbox": "245 193 487 312"}, {"confidence": "0.5842", "file_id": "163", "bbox": "251 143 487 331"}, {"confidence": "0.5833", "file_id": "83", "bbox": "227 214 303 255"}, {"confidence": "0.5822", "file_id": "36", "bbox": "174 54 485 239"}, {"confidence": "0.5789", "file_id": "98", "bbox": "467 72 599 143"}, {"confidence": "0.5782", "file_id": "66", "bbox": "188 354 232 394"}, {"confidence": "0.5752", "file_id": "27", "bbox": "0 167 243 378"}, {"confidence": "0.5710", "file_id": "153", "bbox": "208 201 266 242"}, {"confidence": "0.5685", "file_id": "77", "bbox": "303 291 410 403"}, {"confidence": "0.5654", "file_id": "140", "bbox": "177 23 271 122"}, {"confidence": "0.5652", "file_id": "15", "bbox": "471 395 512 427"}, {"confidence": "0.5623", "file_id": "119", "bbox": "429 120 574 293"}, {"confidence": "0.5615", "file_id": "51", "bbox": "218 226 267 319"}, {"confidence": "0.5599", "file_id": "1", "bbox": "267 243 344 344"}, {"confidence": "0.5599", "file_id": "77", "bbox": "44 169 111 234"}, {"confidence": "0.5565", "file_id": "57", "bbox": "200 303 231 330"}, {"confidence": "0.5560", "file_id": "110", "bbox": "15 184 252 472"}, {"confidence": "0.5488", "file_id": "161", "bbox": "323 261 354 290"}, {"confidence": "0.5482", "file_id": "112", "bbox": "277 350 301 391"}, {"confidence": "0.5480", "file_id": "26", "bbox": "405 279 443 305"}, {"confidence": "0.5452", "file_id": "135", "bbox": "162 158 347 348"}, {"confidence": "0.5351", "file_id": "52", "bbox": "195 186 217 234"}, {"confidence": "0.5323", "file_id": "17", "bbox": "10 199 238 327"}, {"confidence": "0.5261", "file_id": "5", "bbox": "278 237 381 305"}, {"confidence": "0.5254", "file_id": "4", "bbox": "123 180 160 209"}, {"confidence": "0.5204", "file_id": "58", "bbox": "340 135 433 257"}, {"confidence": "0.5203", "file_id": "103", "bbox": "472 338 628 449"}, {"confidence": "0.5179", "file_id": "113", "bbox": "72 40 235 212"}, {"confidence": "0.5154", "file_id": "45", "bbox": "175 126 560 339"}, {"confidence": "0.5141", "file_id": "158", "bbox": "58 323 121 360"}, {"confidence": "0.5120", "file_id": "92", "bbox": "191 97 391 343"}, {"confidence": "0.5031", "file_id": "73", "bbox": "97 200 627 469"}, {"confidence": "0.4934", "file_id": "144", "bbox": "148 20 279 183"}, {"confidence": "0.4811", "file_id": "45", "bbox": "406 246 557 347"}, {"confidence": "0.4564", "file_id": "2", "bbox": "264 126 385 321"}, {"confidence": "0.4562", "file_id": "61", "bbox": "466 278 549 366"}, {"confidence": "0.4559", "file_id": "78", "bbox": "265 191 447 294"}, {"confidence": "0.4437", "file_id": "55", "bbox": "490 317 607 394"}, {"confidence": "0.4422", "file_id": "113", "bbox": "102 35 537 407"}, {"confidence": "0.4414", "file_id": "153", "bbox": "197 203 309 251"}, {"confidence": "0.4393", "file_id": "38", "bbox": "34 76 291 370"}, {"confidence": "0.4376", "file_id": "1", "bbox": "58 130 153 258"}, {"confidence": "0.4339", "file_id": "160", "bbox": "29 76 152 292"}, {"confidence": "0.4306", "file_id": "136", "bbox": "33 339 76 402"}, {"confidence": "0.4287", "file_id": "121", "bbox": "227 278 553 534"}, {"confidence": "0.4202", "file_id": "4", "bbox": "554 234 613 276"}, {"confidence": "0.4188", "file_id": "173", "bbox": "409 98 466 150"}, {"confidence": "0.4181", "file_id": "18", "bbox": "85 8 427 525"}, {"confidence": "0.4128", "file_id": "170", "bbox": "1 355 64 411"}, {"confidence": "0.4082", "file_id": "163", "bbox": "334 141 486 253"}, {"confidence": "0.4014", "file_id": "43", "bbox": "24 2 312 291"}, {"confidence": "0.3971", "file_id": "73", "bbox": "338 56 362 90"}, {"confidence": "0.3942", "file_id": "161", "bbox": "60 279 99 322"}, {"confidence": "0.3911", "file_id": "155", "bbox": "26 293 387 545"}, {"confidence": "0.3901", "file_id": "14", "bbox": "51 273 435 457"}, {"confidence": "0.3893", "file_id": "105", "bbox": "226 74 620 475"}, {"confidence": "0.3885", "file_id": "48", "bbox": "526 279 567 311"}, {"confidence": "0.3820", "file_id": "122", "bbox": "65 28 162 108"}, {"confidence": "0.3727", "file_id": "121", "bbox": "150 113 210 202"}, {"confidence": "0.3658", "file_id": "138", "bbox": "152 124 424 441"}, {"confidence": "0.3613", "file_id": "78", "bbox": "130 157 219 265"}, {"confidence": "0.3611", "file_id": "113", "bbox": "296 59 473 134"}, {"confidence": "0.3598", "file_id": "155", "bbox": "77 162 362 395"}, {"confidence": "0.3577", "file_id": "58", "bbox": "267 226 345 290"}, {"confidence": "0.3514", "file_id": "64", "bbox": "275 138 302 185"}, {"confidence": "0.3508", "file_id": "26", "bbox": "133 287 172 321"}, {"confidence": "0.3491", "file_id": "166", "bbox": "99 217 175 293"}, {"confidence": "0.3479", "file_id": "73", "bbox": "286 59 318 110"}, {"confidence": "0.3467", "file_id": "124", "bbox": "112 209 152 270"}, {"confidence": "0.3409", "file_id": "51", "bbox": "430 195 468 267"}, {"confidence": "0.3399", "file_id": "25", "bbox": "128 260 186 340"}, {"confidence": "0.3379", "file_id": "173", "bbox": "426 96 469 132"}, {"confidence": "0.3378", "file_id": "152", "bbox": "119 217 138 239"}, {"confidence": "0.3376", "file_id": "63", "bbox": "230 21 499 302"}, {"confidence": "0.3298", "file_id": "13", "bbox": "116 355 140 383"}, {"confidence": "0.3279", "file_id": "25", "bbox": "121 277 160 337"}, {"confidence": "0.3277", "file_id": "152", "bbox": "111 214 129 242"}, {"confidence": "0.3272", "file_id": "13", "bbox": "495 408 524 452"}, {"confidence": "0.3238", "file_id": "70", "bbox": "256 334 285 366"}, {"confidence": "0.3084", "file_id": "52", "bbox": "196 197 215 221"}, {"confidence": "0.3045", "file_id": "1", "bbox": "472 186 589 281"}, {"confidence": "0.3023", "file_id": "108", "bbox": "26 29 526 255"}, {"confidence": "0.3022", "file_id": "48", "bbox": "0 203 381 477"}, {"confidence": "0.3002", "file_id": "101", "bbox": "284 268 340 351"}]